pug/__init__.py
pug/data/__init__.py
pug/data/constant.py
pug/data/corpus.py
pug/data/gmm.py
pug/data/posdef.py
pug/data/skeleton.py
pug/data/twit.py
pug/data/weather.py
pug/data/cache/LICENSE
pug/data/cache/README
pug/data/cache/airport.locations.json
pug/data/cache/shakespeare-complete-works-meta.json
pug/data/cache/shakespeare-complete-works.txt.gz
pug_data-0.0.4.dist-info/DESCRIPTION.rst
pug_data-0.0.4.dist-info/METADATA
pug_data-0.0.4.dist-info/RECORD
pug_data-0.0.4.dist-info/WHEEL
pug_data-0.0.4.dist-info/metadata.json
pug_data-0.0.4.dist-info/pbr.json
pug_data-0.0.4.dist-info/top_level.txt
